pandoc_quotes/__init__.py
pandoc_quotes/quot-marks.yaml
pandoc_quotes-0.6.0.data/scripts/pandoc-quotes
pandoc_quotes-0.6.0.dist-info/METADATA
pandoc_quotes-0.6.0.dist-info/RECORD
pandoc_quotes-0.6.0.dist-info/WHEEL
pandoc_quotes-0.6.0.dist-info/top_level.txt
