Metadata-Version: 2.1
Name: pandoc-quotes
Version: 0.6.0
Summary: Pandoc filter that adapts quotation marks.
Home-page: https://github.com/odkr/pandoc-quotes/
Author: Odin Kroeger
Author-email: epnzdp@maskr.me
License: MIT
Project-URL: Source, https://github.com/odkr/pandoc-quotes/
Project-URL: Tracker, https://github.com/odkr/pandoc-quotes/issues
Keywords: pandoc quotation marks
Platform: UNKNOWN
Classifier: Development Status :: 4 - Beta
Classifier: License :: OSI Approved :: MIT License
Classifier: Programming Language :: Python :: 2.7
Classifier: Environment :: Console
Classifier: Operating System :: OS Independent
Classifier: Topic :: Text Processing :: Filters
Requires-Python: >=2.7,<4
Requires-Dist: panflute
Requires-Dist: pyyaml
